scripthelper/__init__.py
scripthelper/py.typed
scripthelper-25.1.dist-info/METADATA
scripthelper-25.1.dist-info/WHEEL
scripthelper-25.1.dist-info/licenses/LICENSE
scripthelper-25.1.dist-info/RECORD
