Metadata-Version: 2.4
Name: scripthelper
Version: 25.1
Summary: Helper module for creating simple Python scripts
Project-URL: Homepage, https://github.com/presidento/scripthelper
Project-URL: Changelog, https://github.com/presidento/scripthelper/blob/main/CHANGELOG.md
Author-email: Máté Farkas <fm@farkas-mate.hu>
License: MIT License
License-File: LICENSE
Classifier: Development Status :: 5 - Production/Stable
Classifier: Intended Audience :: Developers
Classifier: Intended Audience :: System Administrators
Classifier: License :: OSI Approved :: MIT License
Classifier: Operating System :: OS Independent
Classifier: Programming Language :: Python :: 3.9
Classifier: Programming Language :: Python :: 3.10
Classifier: Programming Language :: Python :: 3.11
Classifier: Programming Language :: Python :: 3.12
Classifier: Programming Language :: Python :: 3.13
Classifier: Programming Language :: Python :: 3.14
Classifier: Topic :: Utilities
Classifier: Typing :: Typed
Requires-Python: >=3.9
Requires-Dist: coloredlogs>=10.0
Requires-Dist: persistedstate>=23.6
Requires-Dist: prettyprinter>=0.18.0
Requires-Dist: stackprinter>=0.2.10
Requires-Dist: tqdm>=4.31.1
